{
  "v": 6,
  "name": "Inbox",
  "folders": [],
  "requests": [
    {
      "v": "11",
      "name": "login",
      "method": "POST",
      "endpoint": "<<PRE_PROD_URL>>/api/accounts/login",
      "params": [],
      "headers": [],
      "preRequestScript": "",
      "testScript": "",
      "auth": {
        "authType": "inherit",
        "authActive": true
      },
      "body": {
        "contentType": "application/json",
        "body": "{\"username\":\"jayed@myalice.ai\",\"password\":\"Jayed1234\\u0021\",\"dashboard_language\":\"english\"}"
      },
      "requestVariables": [],
      "responses": {}
    },
    {
      "v": "11",
      "name": "info",
      "method": "GET",
      "endpoint": "<<PRE_PROD_URL>>/api/accounts/info",
      "params": [],
      "headers": [
        {
          "key": "Authorization",
          "value": "Token <<TOKEN>>",
          "active": true,
          "description": ""
        }
      ],
      "preRequestScript": "",
      "testScript": "",
      "auth": {
        "authType": "inherit",
        "authActive": true
      },
      "body": {
        "contentType": null,
        "body": null
      },
      "requestVariables": [],
      "responses": {}
    },
    {
      "v": "11",
      "name": "plans",
      "method": "GET",
      "endpoint": "<<PRE_PROD_URL>>/api/billing/plans",
      "params": [],
      "headers": [
        {
          "key": "Authorization",
          "value": "Token <<TOKEN>>",
          "active": true,
          "description": ""
        }
      ],
      "preRequestScript": "",
      "testScript": "",
      "auth": {
        "authType": "inherit",
        "authActive": true
      },
      "body": {
        "contentType": null,
        "body": null
      },
      "requestVariables": [],
      "responses": {}
    },
    {
      "v": "11",
      "name": "teams",
      "method": "GET",
      "endpoint": "<<PRE_PROD_URL>>/api/dashboard/teams",
      "params": [],
      "headers": [
        {
          "key": "Authorization",
          "value": "Token <<TOKEN>>",
          "active": true,
          "description": ""
        }
      ],
      "preRequestScript": "",
      "testScript": "",
      "auth": {
        "authType": "inherit",
        "authActive": true
      },
      "body": {
        "contentType": null,
        "body": null
      },
      "requestVariables": [],
      "responses": {}
    },
    {
      "v": "11",
      "name": "permissions",
      "method": "GET",
      "endpoint": "<<PRE_PROD_URL>>/api/bots/projects/1996/permissions",
      "params": [],
      "headers": [
        {
          "key": "Authorization",
          "value": "Token <<TOKEN>>",
          "active": true,
          "description": ""
        }
      ],
      "preRequestScript": "",
      "testScript": "",
      "auth": {
        "authType": "inherit",
        "authActive": true
      },
      "body": {
        "contentType": null,
        "body": null
      },
      "requestVariables": [],
      "responses": {}
    },
    {
      "v": "11",
      "name": "details",
      "method": "GET",
      "endpoint": "<<PRE_PROD_URL>>/api/dashboard/team/1996/details",
      "params": [],
      "headers": [
        {
          "key": "Authorization",
          "value": "Token <<TOKEN>>",
          "active": true,
          "description": ""
        }
      ],
      "preRequestScript": "",
      "testScript": "",
      "auth": {
        "authType": "inherit",
        "authActive": true
      },
      "body": {
        "contentType": null,
        "body": null
      },
      "requestVariables": [],
      "responses": {}
    },
    {
      "v": "11",
      "name": "access",
      "method": "GET",
      "endpoint": "<<PRE_PROD_URL>>/api/bots/projects/1996/access",
      "params": [],
      "headers": [
        {
          "key": "Authorization",
          "value": "Token <<TOKEN>>",
          "active": true,
          "description": ""
        }
      ],
      "preRequestScript": "",
      "testScript": "",
      "auth": {
        "authType": "inherit",
        "authActive": true
      },
      "body": {
        "contentType": null,
        "body": null
      },
      "requestVariables": [],
      "responses": {}
    },
    {
      "v": "11",
      "name": "ticket-assignment-count",
      "method": "GET",
      "endpoint": "<<PRE_PROD_URL>>/edge/dashboard/projects/1996/ticket-assignment-count",
      "params": [],
      "headers": [
        {
          "key": "Authorization",
          "value": "Token <<TOKEN>>",
          "active": true,
          "description": ""
        }
      ],
      "preRequestScript": "",
      "testScript": "",
      "auth": {
        "authType": "inherit",
        "authActive": true
      },
      "body": {
        "contentType": null,
        "body": null
      },
      "requestVariables": [],
      "responses": {}
    },
    {
      "v": "11",
      "name": "platform-ticket-assignment-reports",
      "method": "GET",
      "endpoint": "<<PRE_PROD_URL>>/edge/dashboard/projects/1996/platform-ticket-assignment-reports",
      "params": [],
      "headers": [
        {
          "key": "Authorization",
          "value": "Token <<TOKEN>>",
          "active": true,
          "description": ""
        }
      ],
      "preRequestScript": "",
      "testScript": "",
      "auth": {
        "authType": "inherit",
        "authActive": true
      },
      "body": {
        "contentType": null,
        "body": null
      },
      "requestVariables": [],
      "responses": {}
    },
    {
      "v": "11",
      "name": "assigned-agents",
      "method": "GET",
      "endpoint": "<<PRE_PROD_URL>>/edge/dashboard/projects/1996/assigned-agents",
      "params": [],
      "headers": [
        {
          "key": "Authorization",
          "value": "Token <<TOKEN>>",
          "active": true,
          "description": ""
        }
      ],
      "preRequestScript": "",
      "testScript": "",
      "auth": {
        "authType": "inherit",
        "authActive": true
      },
      "body": {
        "contentType": null,
        "body": null
      },
      "requestVariables": [],
      "responses": {}
    },
    {
      "v": "11",
      "name": "get-inbox-preset-filters",
      "method": "GET",
      "endpoint": "<<PRE_PROD_URL>>/edge/crm/projects/1996/get-inbox-preset-filters",
      "params": [],
      "headers": [
        {
          "key": "Authorization",
          "value": "Token <<TOKEN>>",
          "active": true,
          "description": ""
        }
      ],
      "preRequestScript": "",
      "testScript": "",
      "auth": {
        "authType": "inherit",
        "authActive": true
      },
      "body": {
        "contentType": null,
        "body": null
      },
      "requestVariables": [],
      "responses": {}
    },
    {
      "v": "11",
      "name": "tickets",
      "method": "GET",
      "endpoint": "<<PRE_PROD_URL>>/edge/crm/projects/1996/tickets",
      "params": [],
      "headers": [
        {
          "key": "Authorization",
          "value": "Token <<TOKEN>>",
          "active": true,
          "description": ""
        },
        {
          "key": "limit",
          "value": "100",
          "active": true,
          "description": ""
        },
        {
          "key": "offset",
          "value": "0",
          "active": true,
          "description": ""
        },
        {
          "key": "order",
          "value": "desc",
          "active": true,
          "description": ""
        },
        {
          "key": "queue",
          "value": "all",
          "active": true,
          "description": ""
        },
        {
          "key": "search",
          "value": "",
          "active": true,
          "description": ""
        },
        {
          "key": "is_resolved",
          "value": "0",
          "active": true,
          "description": ""
        },
        {
          "key": "is_on_hold",
          "value": "0",
          "active": true,
          "description": ""
        },
        {
          "key": "channels",
          "value": "all",
          "active": true,
          "description": ""
        },
        {
          "key": "agents",
          "value": "all",
          "active": true,
          "description": ""
        },
        {
          "key": "groups",
          "value": "all",
          "active": true,
          "description": ""
        },
        {
          "key": "tags",
          "value": "all",
          "active": true,
          "description": ""
        },
        {
          "key": "priorities",
          "value": "all",
          "active": true,
          "description": ""
        },
        {
          "key": "start",
          "value": "",
          "active": true,
          "description": ""
        },
        {
          "key": "end",
          "value": "",
          "active": true,
          "description": ""
        }
      ],
      "preRequestScript": "",
      "testScript": "",
      "auth": {
        "authType": "inherit",
        "authActive": true
      },
      "body": {
        "contentType": null,
        "body": null
      },
      "requestVariables": [],
      "responses": {}
    },
    {
      "v": "11",
      "name": "ticket-tags",
      "method": "GET",
      "endpoint": "<<PRE_PROD_URL>>/edge/crm/projects/1996/ticket-tags",
      "params": [],
      "headers": [
        {
          "key": "Authorization",
          "value": "Token <<TOKEN>>",
          "active": true,
          "description": ""
        }
      ],
      "preRequestScript": "",
      "testScript": "",
      "auth": {
        "authType": "inherit",
        "authActive": true
      },
      "body": {
        "contentType": null,
        "body": null
      },
      "requestVariables": [],
      "responses": {}
    },
    {
      "v": "11",
      "name": "groups",
      "method": "GET",
      "endpoint": "<<PRE_PROD_URL>>/edge/bots/projects/1996/groups",
      "params": [],
      "headers": [
        {
          "key": "Authorization",
          "value": "Token <<TOKEN>>",
          "active": true,
          "description": ""
        }
      ],
      "preRequestScript": "",
      "testScript": "",
      "auth": {
        "authType": "inherit",
        "authActive": true
      },
      "body": {
        "contentType": null,
        "body": null
      },
      "requestVariables": [],
      "responses": {}
    },
    {
      "v": "11",
      "name": "get-channels",
      "method": "GET",
      "endpoint": "<<PRE_PROD_URL>>/edge/channels/projects/1996/get-channels",
      "params": [],
      "headers": [
        {
          "key": "Authorization",
          "value": "Token <<TOKEN>>",
          "active": true,
          "description": ""
        }
      ],
      "preRequestScript": "",
      "testScript": "",
      "auth": {
        "authType": "inherit",
        "authActive": true
      },
      "body": {
        "contentType": null,
        "body": null
      },
      "requestVariables": [],
      "responses": {}
    },
    {
      "v": "11",
      "name": "canned-responses",
      "method": "GET",
      "endpoint": "<<PRE_PROD_URL>>/edge/crm/projects/1996/canned-responses",
      "params": [],
      "headers": [
        {
          "key": "Authorization",
          "value": "Token <<TOKEN>>",
          "active": true,
          "description": ""
        }
      ],
      "preRequestScript": "",
      "testScript": "",
      "auth": {
        "authType": "inherit",
        "authActive": true
      },
      "body": {
        "contentType": null,
        "body": null
      },
      "requestVariables": [],
      "responses": {}
    },
    {
      "v": "11",
      "name": "copilot-history",
      "method": "GET",
      "endpoint": "<<PRE_PROD_URL>>/edge/crm/tickets/13659/copilot-history",
      "params": [],
      "headers": [
        {
          "key": "Authorization",
          "value": "Token <<TOKEN>>",
          "active": true,
          "description": ""
        }
      ],
      "preRequestScript": "",
      "testScript": "",
      "auth": {
        "authType": "inherit",
        "authActive": true
      },
      "body": {
        "contentType": null,
        "body": null
      },
      "requestVariables": [],
      "responses": {}
    },
    {
      "v": "11",
      "name": "get-conversation",
      "method": "GET",
      "endpoint": "<<PRE_PROD_URL>>/edge/crm/tickets/13659/get-conversation",
      "params": [],
      "headers": [
        {
          "key": "Authorization",
          "value": "Token <<TOKEN>>",
          "active": true,
          "description": ""
        },
        {
          "key": "limit",
          "value": "100",
          "active": true,
          "description": ""
        }
      ],
      "preRequestScript": "",
      "testScript": "",
      "auth": {
        "authType": "inherit",
        "authActive": true
      },
      "body": {
        "contentType": null,
        "body": null
      },
      "requestVariables": [],
      "responses": {}
    },
    {
      "v": "11",
      "name": "meta",
      "method": "GET",
      "endpoint": "<<PRE_PROD_URL>>/edge/bots/customers/25818/meta",
      "params": [],
      "headers": [
        {
          "key": "Authorization",
          "value": "Token <<TOKEN>>",
          "active": true,
          "description": ""
        }
      ],
      "preRequestScript": "",
      "testScript": "",
      "auth": {
        "authType": "inherit",
        "authActive": true
      },
      "body": {
        "contentType": null,
        "body": null
      },
      "requestVariables": [],
      "responses": {}
    },
    {
      "v": "11",
      "name": "customer/25818",
      "method": "GET",
      "endpoint": "<<PRE_PROD_URL>>/edge/form/entries/customer/25818",
      "params": [],
      "headers": [
        {
          "key": "Authorization",
          "value": "Token <<TOKEN>>",
          "active": true,
          "description": ""
        },
        {
          "key": "limit",
          "value": "10",
          "active": true,
          "description": ""
        },
        {
          "key": "offset",
          "value": "0",
          "active": true,
          "description": ""
        }
      ],
      "preRequestScript": "",
      "testScript": "",
      "auth": {
        "authType": "inherit",
        "authActive": true
      },
      "body": {
        "contentType": null,
        "body": null
      },
      "requestVariables": [],
      "responses": {}
    },
    {
      "v": "11",
      "name": "attributes",
      "method": "GET",
      "endpoint": "<<PRE_PROD_URL>>/edge/crm/projects/1996/attributes",
      "params": [],
      "headers": [
        {
          "key": "Authorization",
          "value": "Token <<TOKEN>>",
          "active": true,
          "description": ""
        }
      ],
      "preRequestScript": "",
      "testScript": "",
      "auth": {
        "authType": "inherit",
        "authActive": true
      },
      "body": {
        "contentType": null,
        "body": null
      },
      "requestVariables": [],
      "responses": {}
    },
    {
      "v": "11",
      "name": "data_lab",
      "method": "GET",
      "endpoint": "<<PRE_PROD_URL>>/api/bots/projects/1996/data_lab",
      "params": [],
      "headers": [
        {
          "key": "Authorization",
          "value": "Token <<TOKEN>>",
          "active": true,
          "description": ""
        }
      ],
      "preRequestScript": "",
      "testScript": "",
      "auth": {
        "authType": "inherit",
        "authActive": true
      },
      "body": {
        "contentType": null,
        "body": null
      },
      "requestVariables": [],
      "responses": {}
    },
    {
      "v": "11",
      "name": "get-ticket-configuration",
      "method": "GET",
      "endpoint": "<<PRE_PROD_URL>>/api/bots/projects/1996/get-ticket-configuration",
      "params": [],
      "headers": [
        {
          "key": "Authorization",
          "value": "Token <<TOKEN>>",
          "active": true,
          "description": ""
        }
      ],
      "preRequestScript": "",
      "testScript": "",
      "auth": {
        "authType": "inherit",
        "authActive": true
      },
      "body": {
        "contentType": null,
        "body": null
      },
      "requestVariables": [],
      "responses": {}
    },
    {
      "v": "11",
      "name": "country-list",
      "method": "GET",
      "endpoint": "<<PRE_PROD_URL>>/api/accounts/country-list",
      "params": [],
      "headers": [
        {
          "key": "Authorization",
          "value": "Token <<TOKEN>>",
          "active": true,
          "description": ""
        }
      ],
      "preRequestScript": "",
      "testScript": "",
      "auth": {
        "authType": "inherit",
        "authActive": true
      },
      "body": {
        "contentType": null,
        "body": null
      },
      "requestVariables": [],
      "responses": {}
    },
    {
      "v": "11",
      "name": "timezone-list",
      "method": "GET",
      "endpoint": "<<PRE_PROD_URL>>/api/accounts/timezone-list",
      "params": [],
      "headers": [
        {
          "key": "Authorization",
          "value": "Token <<TOKEN>>",
          "active": true,
          "description": ""
        }
      ],
      "preRequestScript": "",
      "testScript": "",
      "auth": {
        "authType": "inherit",
        "authActive": true
      },
      "body": {
        "contentType": null,
        "body": null
      },
      "requestVariables": [],
      "responses": {}
    },
    {
      "v": "11",
      "name": "ticket-count-of-agent",
      "method": "GET",
      "endpoint": "<<PRE_PROD_URL>>/edge/dashboard/projects/1996/ticket-count-of-agent",
      "params": [],
      "headers": [
        {
          "key": "Authorization",
          "value": "Token <<TOKEN>>",
          "active": true,
          "description": ""
        },
        {
          "key": "agent_id",
          "value": "1819",
          "active": true,
          "description": ""
        }
      ],
      "preRequestScript": "",
      "testScript": "",
      "auth": {
        "authType": "inherit",
        "authActive": true
      },
      "body": {
        "contentType": null,
        "body": null
      },
      "requestVariables": [],
      "responses": {}
    },
    {
      "v": "11",
      "name": "messenger-chat",
      "method": "POST",
      "endpoint": "<<PRE_PROD_URL>>/edge/crm/tickets/13659/messenger-chat",
      "params": [],
      "headers": [
        {
          "key": "Authorization",
          "value": "Token <<TOKEN>>",
          "active": true,
          "description": ""
        }
      ],
      "preRequestScript": "",
      "testScript": "",
      "auth": {
        "authType": "inherit",
        "authActive": true
      },
      "body": {
        "contentType": "application/json",
        "body": "{\"text\":\"hi\",\"audio\":null,\"image\":null,\"attachments\":[],\"template\":null,\"action\":\"direct_message\"}"
      },
      "requestVariables": [],
      "responses": {}
    }
  ],
  "auth": {
    "authType": "none",
    "authActive": true
  },
  "headers": [],
  "_ref_id": "coll_b84898efdebe47389f4c7eaff01c4fa3"
}